<apicalls>
<call>
<permissions>
<permission>
<name>android.permission.ACCESS_NETWORK_STATE</name>
<apiversion>2.2.3</apiversion>
<apiversion>2.3.6</apiversion>
<apiversion>3.2.2</apiversion>
</permission>
</permissions>
<file>./smali/ru/nashe/android/apps/nasheradio/JScriptObject.java</file>
<line>87</line>
<protected>android/webkit/WebView;-$gt;loadUrl</protected>
<deleted>false</deleted>
</call>
<call>
<permissions>
<permission>
<name>android.permission.WAKE_LOCK</name>
<apiversion>4.1.1</apiversion>
<apiversion>2.2.3</apiversion>
<apiversion>2.3.6</apiversion>
<apiversion>3.2.2</apiversion>
<apiversion>4.0.1</apiversion>
</permission>
</permissions>
<file>./smali/ru/nashe/android/apps/nasheradio/JScriptObject.java</file>
<line>31</line>
<protected>android/media/MediaPlayer;-$gt;stop</protected>
<deleted>false</deleted>
</call>
<call>
<permissions>
<permission>
<name>android.permission.WAKE_LOCK</name>
<apiversion>4.1.1</apiversion>
<apiversion>2.2.3</apiversion>
<apiversion>2.3.6</apiversion>
<apiversion>3.2.2</apiversion>
<apiversion>4.0.1</apiversion>
</permission>
</permissions>
<file>./smali/ru/nashe/android/apps/nasheradio/JScriptObject.java</file>
<line>32</line>
<protected>android/media/MediaPlayer;-$gt;reset</protected>
<deleted>false</deleted>
</call>
<call>
<permissions>
<permission>
<name>android.permission.WAKE_LOCK</name>
<apiversion>4.1.1</apiversion>
<apiversion>2.2.3</apiversion>
<apiversion>2.3.6</apiversion>
<apiversion>3.2.2</apiversion>
<apiversion>4.0.1</apiversion>
</permission>
</permissions>
<file>./smali/ru/nashe/android/apps/nasheradio/JScriptObject.java</file>
<line>37</line>
<protected>android/media/MediaPlayer;-$gt;start</protected>
<deleted>false</deleted>
</call>
<call>
<permissions>
<permission>
<name>android.permission.WAKE_LOCK</name>
<apiversion>4.1.1</apiversion>
<apiversion>2.2.3</apiversion>
<apiversion>2.3.6</apiversion>
<apiversion>3.2.2</apiversion>
<apiversion>4.0.1</apiversion>
</permission>
</permissions>
<file>./smali/ru/nashe/android/apps/nasheradio/JScriptObject.java</file>
<line>56</line>
<protected>android/media/MediaPlayer;-$gt;stop</protected>
<deleted>false</deleted>
</call>
<call>
<permissions>
<permission>
<name>android.permission.WAKE_LOCK</name>
<apiversion>4.1.1</apiversion>
<apiversion>2.2.3</apiversion>
<apiversion>2.3.6</apiversion>
<apiversion>3.2.2</apiversion>
<apiversion>4.0.1</apiversion>
</permission>
</permissions>
<file>./smali/ru/nashe/android/apps/nasheradio/JScriptObject.java</file>
<line>57</line>
<protected>android/media/MediaPlayer;-$gt;reset</protected>
<deleted>false</deleted>
</call>
<call>
<permissions>
<permission>
<name>android.permission.VIBRATE</name>
<apiversion>4.1.1</apiversion>
<apiversion>2.2.3</apiversion>
<apiversion>2.3.6</apiversion>
<apiversion>3.2.2</apiversion>
<apiversion>4.0.1</apiversion>
</permission>
</permissions>
<file>./smali/ru/nashe/android/apps/nasheradio/ServiceHandler.java</file>
<line>65</line>
<protected>android/app/NotificationManager;-$gt;notify</protected>
<deleted>false</deleted>
</call>
<call>
<permissions>
<permission>
<name>android.permission.WAKE_LOCK</name>
<apiversion>4.1.1</apiversion>
<apiversion>2.2.3</apiversion>
<apiversion>2.3.6</apiversion>
<apiversion>3.2.2</apiversion>
<apiversion>4.0.1</apiversion>
</permission>
</permissions>
<file>./smali/ru/nashe/android/apps/nasheradio/ServiceHandler.java</file>
<line>80</line>
<protected>android/media/MediaPlayer;-$gt;stop</protected>
<deleted>false</deleted>
</call>
<call>
<permissions>
<permission>
<name>android.permission.WAKE_LOCK</name>
<apiversion>4.1.1</apiversion>
<apiversion>2.2.3</apiversion>
<apiversion>2.3.6</apiversion>
<apiversion>3.2.2</apiversion>
<apiversion>4.0.1</apiversion>
</permission>
</permissions>
<file>./smali/ru/nashe/android/apps/nasheradio/ServiceHandler.java</file>
<line>119</line>
<protected>android/media/MediaPlayer;-$gt;stop</protected>
<deleted>false</deleted>
</call>
<call>
<permissions>
<permission>
<name>android.permission.WAKE_LOCK</name>
<apiversion>4.1.1</apiversion>
<apiversion>2.2.3</apiversion>
<apiversion>2.3.6</apiversion>
<apiversion>3.2.2</apiversion>
<apiversion>4.0.1</apiversion>
</permission>
</permissions>
<file>./smali/ru/nashe/android/apps/nasheradio/ServiceHandler.java</file>
<line>120</line>
<protected>android/media/MediaPlayer;-$gt;reset</protected>
<deleted>false</deleted>
</call>
<call>
<permissions>
<permission>
<name>android.permission.WAKE_LOCK</name>
<apiversion>4.1.1</apiversion>
<apiversion>2.2.3</apiversion>
<apiversion>2.3.6</apiversion>
<apiversion>3.2.2</apiversion>
<apiversion>4.0.1</apiversion>
</permission>
</permissions>
<file>./smali/ru/nashe/android/apps/nasheradio/ServiceHandler.java</file>
<line>121</line>
<protected>android/media/MediaPlayer;-$gt;release</protected>
<deleted>false</deleted>
</call>
<call>
<permissions>
<permission>
<name>android.permission.WAKE_LOCK</name>
<apiversion>4.1.1</apiversion>
<apiversion>2.2.3</apiversion>
<apiversion>2.3.6</apiversion>
<apiversion>3.2.2</apiversion>
<apiversion>4.0.1</apiversion>
</permission>
</permissions>
<file>./smali/ru/nashe/android/apps/nasheradio/ServiceHandler.java</file>
<line>96</line>
<protected>android/media/MediaPlayer;-$gt;start</protected>
<deleted>false</deleted>
</call>
<call>
<permissions>
<permission>
<name>android.permission.WAKE_LOCK</name>
<apiversion>4.1.1</apiversion>
<apiversion>2.2.3</apiversion>
<apiversion>2.3.6</apiversion>
<apiversion>3.2.2</apiversion>
<apiversion>4.0.1</apiversion>
</permission>
</permissions>
<file>./smali/ru/nashe/android/apps/nasheradio/ServiceHandler.java</file>
<line>131</line>
<protected>android/media/MediaPlayer;-$gt;stop</protected>
<deleted>false</deleted>
</call>
<call>
<permissions>
<permission>
<name>android.permission.WAKE_LOCK</name>
<apiversion>4.1.1</apiversion>
<apiversion>2.2.3</apiversion>
<apiversion>2.3.6</apiversion>
<apiversion>3.2.2</apiversion>
<apiversion>4.0.1</apiversion>
</permission>
</permissions>
<file>./smali/ru/nashe/android/apps/nasheradio/ServiceHandler.java</file>
<line>132</line>
<protected>android/media/MediaPlayer;-$gt;reset</protected>
<deleted>false</deleted>
</call>
<call>
<permissions>
<permission>
<name>android.permission.WAKE_LOCK</name>
<apiversion>4.1.1</apiversion>
<apiversion>2.2.3</apiversion>
<apiversion>2.3.6</apiversion>
<apiversion>3.2.2</apiversion>
<apiversion>4.0.1</apiversion>
</permission>
</permissions>
<file>./smali/ru/nashe/android/apps/nasheradio/ServiceHandler.java</file>
<line>133</line>
<protected>android/media/MediaPlayer;-$gt;release</protected>
<deleted>false</deleted>
</call>
<call>
<permissions>
<permission>
<name>android.permission.ACCESS_NETWORK_STATE</name>
<apiversion>2.2.3</apiversion>
<apiversion>2.3.6</apiversion>
<apiversion>3.2.2</apiversion>
</permission>
</permissions>
<file>./smali/ru/nashe/android/apps/nasheradio/MainActivity.java</file>
<line>193</line>
<protected>android/webkit/WebView;-$gt;loadUrl</protected>
<deleted>false</deleted>
</call>
<call>
<permissions>
<permission>
<name>android.permission.ACCESS_NETWORK_STATE</name>
<apiversion>2.2.3</apiversion>
<apiversion>2.3.6</apiversion>
<apiversion>3.2.2</apiversion>
</permission>
</permissions>
<file>./smali/ru/nashe/android/apps/nasheradio/MainActivity.java</file>
<line>209</line>
<protected>android/webkit/WebView;-$gt;pauseTimers</protected>
<deleted>false</deleted>
</call>
<call>
<permissions>
<permission>
<name>android.permission.ACCESS_NETWORK_STATE</name>
<apiversion>2.2.3</apiversion>
<apiversion>2.3.6</apiversion>
<apiversion>3.2.2</apiversion>
</permission>
</permissions>
<file>./smali/ru/nashe/android/apps/nasheradio/MainActivity.java</file>
<line>215</line>
<protected>android/webkit/WebView;-$gt;resumeTimers</protected>
<deleted>false</deleted>
</call>
</apicalls>
