<?xml version="1.0"?>
<calls>
  <call>
    <file>./smali/com/inoview/mplus/xml/dialog/QuizRecordDialog.java</file>
    <line>349</line>
    <permissions>
      <permission>
        <name>android.permission.WAKE_LOCK</name>
      </permission>
    </permissions>
  </call>
  <call>
    <file>./smali/com/inoview/mplus/xml/dialog/QuizRecordDialog.java</file>
    <line>397</line>
    <permissions>
      <permission>
        <name>android.permission.WAKE_LOCK</name>
      </permission>
    </permissions>
  </call>
  <call>
    <file>./smali/com/inoview/mplus/xml/dialog/QuizRecordDialog.java</file>
    <line>398</line>
    <permissions>
      <permission>
        <name>android.permission.WAKE_LOCK</name>
      </permission>
    </permissions>
  </call>
  <call>
    <file>./smali/com/inoview/mplus/xml/dialog/QuizRecordDialog.java</file>
    <line>522</line>
    <permissions>
      <permission>
        <name>android.permission.WAKE_LOCK</name>
      </permission>
    </permissions>
  </call>
  <call>
    <file>./smali/com/inoview/mplus/xml/dialog/QuizRecordDialog.java</file>
    <line>536</line>
    <permissions>
      <permission>
        <name>android.permission.WAKE_LOCK</name>
      </permission>
    </permissions>
  </call>
  <call>
    <file>./smali/com/inoview/mplus/xml/dialog/QuizRecordDialog.java</file>
    <line>537</line>
    <permissions>
      <permission>
        <name>android.permission.WAKE_LOCK</name>
      </permission>
    </permissions>
  </call>
  <call>
    <file>./smali/com/inoview/mplus/xml/dialog/QuizRecordDialog.java</file>
    <line>556</line>
    <permissions>
      <permission>
        <name>android.permission.WAKE_LOCK</name>
      </permission>
    </permissions>
  </call>
  <call>
    <file>./smali/com/inoview/mplus/xml/dialog/QuizRecordDialog.java</file>
    <line>436</line>
    <permissions>
      <permission>
        <name>android.permission.RECORD_AUDIO</name>
      </permission>
    </permissions>
  </call>
  <call>
    <file>./smali/com/inoview/mplus/xml/dialog/QuizRecordDialog.java</file>
    <line>204</line>
    <permissions>
      <permission>
        <name>android.permission.INTERNET</name>
      </permission>
    </permissions>
  </call>
  <call>
    <file>./smali/com/inoview/mplus/xml/dialog/QuizRecordDialog.java</file>
    <line>206</line>
    <permissions>
      <permission>
        <name>android.permission.INTERNET</name>
      </permission>
    </permissions>
  </call>
  <call>
    <file>./smali/com/inoview/mplus/xml/dialog/QuizRecordDialog.java</file>
    <line>262</line>
    <permissions>
      <permission>
        <name>android.permission.WAKE_LOCK</name>
      </permission>
    </permissions>
  </call>
  <call>
    <file>./smali/com/inoview/mplus/xml/dialog/QuizRecordDialog.java</file>
    <line>262</line>
    <permissions>
      <permission>
        <name>android.permission.WAKE_LOCK</name>
      </permission>
    </permissions>
  </call>
  <call>
    <file>./smali/com/inoview/mplus/xml/dialog/QuizRecordDialog$2.java</file>
    <line>156</line>
    <permissions>
      <permission>
        <name>android.permission.WAKE_LOCK</name>
      </permission>
    </permissions>
  </call>
  <call>
    <file>./smali/com/inoview/mplus/xml/dialog/QuizRecordDialog$2.java</file>
    <line>157</line>
    <permissions>
      <permission>
        <name>android.permission.WAKE_LOCK</name>
      </permission>
    </permissions>
  </call>
  <call>
    <file>./smali/com/inoview/mplus/xml/mainlayout/MPlusPlayerSecondActivity.java</file>
    <line>1054</line>
    <permissions>
      <permission>
        <name>android.permission.ACCESS_NETWORK_STATE</name>
      </permission>
    </permissions>
  </call>
  <call>
    <file>./smali/com/inoview/mplus/xml/mainlayout/MPlusPlayerSecondActivity.java</file>
    <line>242</line>
    <permissions>
      <permission>
        <name>android.permission.ACCESS_NETWORK_STATE</name>
      </permission>
    </permissions>
  </call>
  <call>
    <file>./smali/com/inoview/mplus/xml/mainlayout/MPlusPlayerSecondActivity.java</file>
    <line>243</line>
    <permissions>
      <permission>
        <name>android.permission.ACCESS_NETWORK_STATE</name>
      </permission>
    </permissions>
  </call>
  <call>
    <file>./smali/com/inoview/mplus/xml/mainlayout/MPlusPlayerSecondActivity.java</file>
    <line>615</line>
    <permissions>
      <permission>
        <name>android.permission.ACCESS_NETWORK_STATE</name>
      </permission>
    </permissions>
  </call>
  <call>
    <file>./smali/com/inoview/mplus/xml/mainlayout/MPlusPlayerSecondActivity.java</file>
    <line>989</line>
    <permissions>
      <permission>
        <name>android.permission.ACCESS_NETWORK_STATE</name>
      </permission>
    </permissions>
  </call>
  <call>
    <file>./smali/com/inoview/mplus/xml/mainlayout/MPlusPlayerSecondActivity.java</file>
    <line>993</line>
    <permissions>
      <permission>
        <name>android.permission.ACCESS_NETWORK_STATE</name>
      </permission>
    </permissions>
  </call>
  <call>
    <file>./smali/com/inoview/mplus/xml/mainlayout/MPlusPlayerSecondActivity$1.java</file>
    <line>1373</line>
    <permissions>
      <permission>
        <name>android.permission.ACCESS_NETWORK_STATE</name>
      </permission>
    </permissions>
  </call>
  <call>
    <file>./smali/com/inoview/mplus/xml/maincontroller/MPlusController$65.java</file>
    <line>6344</line>
    <permissions>
      <permission>
        <name>android.permission.WAKE_LOCK</name>
      </permission>
    </permissions>
  </call>
  <call>
    <file>./smali/com/inoview/mplus/xml/maincontroller/MPlusController$65.java</file>
    <line>6359</line>
    <permissions>
      <permission>
        <name>android.permission.WAKE_LOCK</name>
      </permission>
    </permissions>
  </call>
  <call>
    <file>./smali/com/inoview/mplus/xml/maincontroller/MPlusController$3.java</file>
    <line>6529</line>
    <permissions>
      <permission>
        <name>android.permission.WAKE_LOCK</name>
      </permission>
    </permissions>
  </call>
  <call>
    <file>./smali/com/inoview/mplus/xml/maincontroller/MPlusController$3.java</file>
    <line>6534</line>
    <permissions>
      <permission>
        <name>android.permission.WAKE_LOCK</name>
      </permission>
    </permissions>
  </call>
  <call>
    <file>./smali/com/inoview/mplus/xml/maincontroller/MPlusController$66.java</file>
    <line>6429</line>
    <permissions>
      <permission>
        <name>android.permission.WAKE_LOCK</name>
      </permission>
    </permissions>
  </call>
  <call>
    <file>./smali/com/inoview/mplus/xml/maincontroller/MPlusController$66.java</file>
    <line>6445</line>
    <permissions>
      <permission>
        <name>android.permission.WAKE_LOCK</name>
      </permission>
    </permissions>
  </call>
  <call>
    <file>./smali/com/inoview/mplus/xml/maincontroller/MPlusController.java</file>
    <line>550</line>
    <permissions>
      <permission>
        <name>android.permission.INTERNET</name>
      </permission>
    </permissions>
  </call>
  <call>
    <file>./smali/com/inoview/mplus/xml/maincontroller/MPlusController.java</file>
    <line>551</line>
    <permissions>
      <permission>
        <name>android.permission.INTERNET</name>
      </permission>
    </permissions>
  </call>
  <call>
    <file>./smali/com/inoview/mplus/xml/maincontroller/MPlusController.java</file>
    <line>2662</line>
    <permissions>
      <permission>
        <name>android.permission.WAKE_LOCK</name>
      </permission>
    </permissions>
  </call>
  <call>
    <file>./smali/com/inoview/mplus/xml/maincontroller/MPlusController.java</file>
    <line>2663</line>
    <permissions>
      <permission>
        <name>android.permission.WAKE_LOCK</name>
      </permission>
    </permissions>
  </call>
  <call>
    <file>./smali/com/inoview/mplus/xml/maincontroller/MPlusController.java</file>
    <line>2725</line>
    <permissions>
      <permission>
        <name>android.permission.ACCESS_NETWORK_STATE</name>
      </permission>
      <permission>
        <name>android.permission.WAKE_LOCK</name>
      </permission>
    </permissions>
  </call>
  <call>
    <file>./smali/com/inoview/mplus/xml/maincontroller/MPlusController.java</file>
    <line>4645</line>
    <permissions>
      <permission>
        <name>android.permission.ACCESS_NETWORK_STATE</name>
      </permission>
    </permissions>
  </call>
  <call>
    <file>./smali/com/inoview/mplus/xml/maincontroller/MPlusController.java</file>
    <line>4698</line>
    <permissions>
      <permission>
        <name>android.permission.ACCESS_NETWORK_STATE</name>
      </permission>
    </permissions>
  </call>
  <call>
    <file>./smali/com/inoview/mplus/xml/maincontroller/MPlusController.java</file>
    <line>4702</line>
    <permissions>
      <permission>
        <name>android.permission.ACCESS_NETWORK_STATE</name>
      </permission>
    </permissions>
  </call>
  <call>
    <file>./smali/com/inoview/mplus/xml/maincontroller/MPlusController.java</file>
    <line>4706</line>
    <permissions>
      <permission>
        <name>android.permission.ACCESS_NETWORK_STATE</name>
      </permission>
    </permissions>
  </call>
  <call>
    <file>./smali/com/inoview/mplus/xml/maincontroller/MPlusController.java</file>
    <line>4725</line>
    <permissions>
      <permission>
        <name>android.permission.WAKE_LOCK</name>
      </permission>
    </permissions>
  </call>
  <call>
    <file>./smali/com/inoview/mplus/xml/maincontroller/MPlusController.java</file>
    <line>4739</line>
    <permissions>
      <permission>
        <name>android.permission.WAKE_LOCK</name>
      </permission>
    </permissions>
  </call>
  <call>
    <file>./smali/com/inoview/mplus/xml/maincontroller/MPlusController.java</file>
    <line>5042</line>
    <permissions>
      <permission>
        <name>android.permission.WAKE_LOCK</name>
      </permission>
    </permissions>
  </call>
  <call>
    <file>./smali/com/inoview/mplus/xml/maincontroller/MPlusController.java</file>
    <line>4812</line>
    <permissions>
      <permission>
        <name>android.permission.WAKE_LOCK</name>
      </permission>
    </permissions>
  </call>
  <call>
    <file>./smali/com/inoview/mplus/xml/maincontroller/MPlusController.java</file>
    <line>4851</line>
    <permissions>
      <permission>
        <name>android.permission.WAKE_LOCK</name>
      </permission>
    </permissions>
  </call>
  <call>
    <file>./smali/com/inoview/mplus/xml/maincontroller/MPlusController.java</file>
    <line>4891</line>
    <permissions>
      <permission>
        <name>android.permission.WAKE_LOCK</name>
      </permission>
    </permissions>
  </call>
  <call>
    <file>./smali/com/inoview/mplus/xml/maincontroller/MPlusController.java</file>
    <line>4928</line>
    <permissions>
      <permission>
        <name>android.permission.WAKE_LOCK</name>
      </permission>
    </permissions>
  </call>
  <call>
    <file>./smali/com/inoview/mplus/xml/maincontroller/MPlusController.java</file>
    <line>4967</line>
    <permissions>
      <permission>
        <name>android.permission.WAKE_LOCK</name>
      </permission>
    </permissions>
  </call>
  <call>
    <file>./smali/com/inoview/mplus/xml/maincontroller/MPlusController.java</file>
    <line>5005</line>
    <permissions>
      <permission>
        <name>android.permission.WAKE_LOCK</name>
      </permission>
    </permissions>
  </call>
  <call>
    <file>./smali/com/inoview/mplus/xml/maincontroller/MPlusController.java</file>
    <line>5081</line>
    <permissions>
      <permission>
        <name>android.permission.WAKE_LOCK</name>
      </permission>
    </permissions>
  </call>
  <call>
    <file>./smali/com/inoview/mplus/xml/maincontroller/MPlusController.java</file>
    <line>5200</line>
    <permissions>
      <permission>
        <name>android.permission.WAKE_LOCK</name>
      </permission>
    </permissions>
  </call>
  <call>
    <file>./smali/com/inoview/mplus/xml/maincontroller/MPlusController.java</file>
    <line>5229</line>
    <permissions>
      <permission>
        <name>android.permission.WAKE_LOCK</name>
      </permission>
    </permissions>
  </call>
  <call>
    <file>./smali/com/inoview/mplus/xml/maincontroller/MPlusController.java</file>
    <line>5246</line>
    <permissions>
      <permission>
        <name>android.permission.WAKE_LOCK</name>
      </permission>
    </permissions>
  </call>
  <call>
    <file>./smali/com/inoview/mplus/xml/maincontroller/MPlusController.java</file>
    <line>5263</line>
    <permissions>
      <permission>
        <name>android.permission.WAKE_LOCK</name>
      </permission>
    </permissions>
  </call>
  <call>
    <file>./smali/com/inoview/mplus/xml/maincontroller/MPlusController.java</file>
    <line>5288</line>
    <permissions>
      <permission>
        <name>android.permission.WAKE_LOCK</name>
      </permission>
    </permissions>
  </call>
  <call>
    <file>./smali/com/inoview/mplus/xml/maincontroller/MPlusController.java</file>
    <line>5310</line>
    <permissions>
      <permission>
        <name>android.permission.WAKE_LOCK</name>
      </permission>
    </permissions>
  </call>
  <call>
    <file>./smali/com/inoview/mplus/xml/maincontroller/MPlusController.java</file>
    <line>5325</line>
    <permissions>
      <permission>
        <name>android.permission.WAKE_LOCK</name>
      </permission>
    </permissions>
  </call>
  <call>
    <file>./smali/com/inoview/mplus/xml/maincontroller/MPlusController.java</file>
    <line>5365</line>
    <permissions>
      <permission>
        <name>android.permission.WAKE_LOCK</name>
      </permission>
    </permissions>
  </call>
  <call>
    <file>./smali/com/inoview/mplus/xml/maincontroller/MPlusController.java</file>
    <line>5383</line>
    <permissions>
      <permission>
        <name>android.permission.WAKE_LOCK</name>
      </permission>
    </permissions>
  </call>
  <call>
    <file>./smali/com/inoview/mplus/xml/maincontroller/MPlusController.java</file>
    <line>5422</line>
    <permissions>
      <permission>
        <name>android.permission.WAKE_LOCK</name>
      </permission>
    </permissions>
  </call>
  <call>
    <file>./smali/com/inoview/mplus/xml/maincontroller/MPlusController.java</file>
    <line>5464</line>
    <permissions>
      <permission>
        <name>android.permission.WAKE_LOCK</name>
      </permission>
    </permissions>
  </call>
  <call>
    <file>./smali/com/inoview/mplus/xml/maincontroller/MPlusController.java</file>
    <line>5806</line>
    <permissions>
      <permission>
        <name>android.permission.WAKE_LOCK</name>
      </permission>
    </permissions>
  </call>
  <call>
    <file>./smali/com/inoview/mplus/xml/maincontroller/MPlusController.java</file>
    <line>5608</line>
    <permissions>
      <permission>
        <name>android.permission.WAKE_LOCK</name>
      </permission>
    </permissions>
  </call>
  <call>
    <file>./smali/com/inoview/mplus/xml/maincontroller/MPlusController.java</file>
    <line>968</line>
    <permissions>
      <permission>
        <name>android.permission.ACCESS_NETWORK_STATE</name>
      </permission>
    </permissions>
  </call>
  <call>
    <file>./smali/com/inoview/mplus/xml/maincontroller/MPlusController.java</file>
    <line>971</line>
    <permissions>
      <permission>
        <name>android.permission.ACCESS_NETWORK_STATE</name>
      </permission>
    </permissions>
  </call>
  <call>
    <file>./smali/com/inoview/mplus/xml/maincontroller/MPlusController.java</file>
    <line>731</line>
    <permissions>
      <permission>
        <name>android.permission.WAKE_LOCK</name>
      </permission>
    </permissions>
  </call>
  <call>
    <file>./smali/com/inoview/mplus/xml/maincontroller/MPlusController.java</file>
    <line>749</line>
    <permissions>
      <permission>
        <name>android.permission.WAKE_LOCK</name>
      </permission>
    </permissions>
  </call>
  <call>
    <file>./smali/com/inoview/mplus/xml/maincontroller/MPlusController.java</file>
    <line>663</line>
    <permissions>
      <permission>
        <name>android.permission.WAKE_LOCK</name>
      </permission>
    </permissions>
  </call>
  <call>
    <file>./smali/com/inoview/mplus/xml/maincontroller/MPlusController.java</file>
    <line>664</line>
    <permissions>
      <permission>
        <name>android.permission.WAKE_LOCK</name>
      </permission>
    </permissions>
  </call>
  <call>
    <file>./smali/com/inoview/mplus/xml/maincontroller/MPlusController.java</file>
    <line>426</line>
    <permissions>
      <permission>
        <name>android.permission.WAKE_LOCK</name>
      </permission>
    </permissions>
  </call>
  <call>
    <file>./smali/com/inoview/mplus/xml/maincontroller/MPlusController.java</file>
    <line>1910</line>
    <permissions>
      <permission>
        <name>android.permission.ACCESS_NETWORK_STATE</name>
      </permission>
    </permissions>
  </call>
  <call>
    <file>./smali/com/inoview/mplus/xml/maincontroller/MPlusController.java</file>
    <line>1924</line>
    <permissions>
      <permission>
        <name>android.permission.ACCESS_NETWORK_STATE</name>
      </permission>
    </permissions>
  </call>
  <call>
    <file>./smali/com/inoview/mplus/xml/maincontroller/MPlusController.java</file>
    <line>1960</line>
    <permissions>
      <permission>
        <name>android.permission.ACCESS_NETWORK_STATE</name>
      </permission>
    </permissions>
  </call>
  <call>
    <file>./smali/com/inoview/mplus/xml/maincontroller/MPlusController.java</file>
    <line>1509</line>
    <permissions>
      <permission>
        <name>android.permission.WAKE_LOCK</name>
      </permission>
    </permissions>
  </call>
  <call>
    <file>./smali/com/inoview/mplus/xml/maincontroller/MPlusController.java</file>
    <line>1581</line>
    <permissions>
      <permission>
        <name>android.permission.WAKE_LOCK</name>
      </permission>
    </permissions>
  </call>
  <call>
    <file>./smali/com/inoview/mplus/xml/maincontroller/MPlusController.java</file>
    <line>2547</line>
    <permissions>
      <permission>
        <name>android.permission.WAKE_LOCK</name>
      </permission>
    </permissions>
  </call>
  <call>
    <file>./smali/com/inoview/mplus/xml/maincontroller/MPlusController.java</file>
    <line>2548</line>
    <permissions>
      <permission>
        <name>android.permission.WAKE_LOCK</name>
      </permission>
    </permissions>
  </call>
  <call>
    <file>./smali/com/inoview/mplus/xml/maincontroller/MPlusController$2.java</file>
    <line>4449</line>
    <permissions>
      <permission>
        <name>android.permission.WAKE_LOCK</name>
      </permission>
    </permissions>
  </call>
  <call>
    <file>./smali/com/inoview/mplus/xml/maincontroller/MPlusController$6.java</file>
    <line>842</line>
    <permissions>
      <permission>
        <name>android.permission.WRITE_SETTINGS</name>
      </permission>
    </permissions>
  </call>
  <call>
    <file>./smali/com/inoview/mplus/xml/maincontroller/MPlusController$30.java</file>
    <line>3141</line>
    <permissions>
      <permission>
        <name>android.permission.ACCESS_NETWORK_STATE</name>
      </permission>
    </permissions>
  </call>
  <call>
    <file>./smali/com/inoview/mplus/xml/maincontroller/MPlusController$30.java</file>
    <line>3144</line>
    <permissions>
      <permission>
        <name>android.permission.ACCESS_NETWORK_STATE</name>
      </permission>
    </permissions>
  </call>
  <call>
    <file>./smali/com/inoview/mplus/xml/maincontroller/MPlusController$30.java</file>
    <line>3147</line>
    <permissions>
      <permission>
        <name>android.permission.ACCESS_NETWORK_STATE</name>
      </permission>
    </permissions>
  </call>
  <call>
    <file>./smali/com/inoview/mplus/xml/maincontroller/MPlusController$64.java</file>
    <line>6235</line>
    <permissions>
      <permission>
        <name>android.permission.WAKE_LOCK</name>
      </permission>
    </permissions>
  </call>
  <call>
    <file>./smali/com/inoview/mplus/xml/maincontroller/MPlusController$64.java</file>
    <line>6249</line>
    <permissions>
      <permission>
        <name>android.permission.WAKE_LOCK</name>
      </permission>
    </permissions>
  </call>
  <call>
    <file>./smali/com/inoview/mplus/xml/download/DownLoadQueue.java</file>
    <line>116</line>
    <permissions>
      <permission>
        <name>android.permission.INTERNET</name>
      </permission>
    </permissions>
  </call>
  <call>
    <file>./smali/com/inoview/mplus/xml/download/DownLoadQueue.java</file>
    <line>118</line>
    <permissions>
      <permission>
        <name>android.permission.INTERNET</name>
      </permission>
    </permissions>
  </call>
  <call>
    <file>./smali/com/inoview/mplus/xml/parcing/ParceJason.java</file>
    <line>49</line>
    <permissions>
      <permission>
        <name>android.permission.INTERNET</name>
      </permission>
    </permissions>
  </call>
  <call>
    <file>./smali/com/inoview/mplus/xml/parcing/ParceJason.java</file>
    <line>53</line>
    <permissions>
      <permission>
        <name>android.permission.INTERNET</name>
      </permission>
    </permissions>
  </call>
  <call>
    <file>./smali/com/inoview/mplus/xml/parcing/ParceAllJsons.java</file>
    <line>44</line>
    <permissions>
      <permission>
        <name>android.permission.INTERNET</name>
      </permission>
    </permissions>
  </call>
  <call>
    <file>./smali/com/inoview/mplus/xml/parcing/ParceAllJsons.java</file>
    <line>47</line>
    <permissions>
      <permission>
        <name>android.permission.INTERNET</name>
      </permission>
    </permissions>
  </call>
  <call>
    <file>./smali/com/inoview/mplus/xml/parcing/ParceAllJsons.java</file>
    <line>141</line>
    <permissions>
      <permission>
        <name>android.permission.INTERNET</name>
      </permission>
    </permissions>
  </call>
  <call>
    <file>./smali/com/inoview/mplus/xml/parcing/ParceAllJsons.java</file>
    <line>144</line>
    <permissions>
      <permission>
        <name>android.permission.INTERNET</name>
      </permission>
    </permissions>
  </call>
  <call>
    <file>./smali/com/inoview/mplus/xml/webview/MyWebView.java</file>
    <line>10</line>
    <permissions>
      <permission>
        <name>android.permission.INTERNET</name>
      </permission>
    </permissions>
  </call>
  <call>
    <file>./smali/com/inoview/mplus/xml/webview/MyWebViewClient.java</file>
    <line>30</line>
    <permissions>
      <permission>
        <name>android.permission.ACCESS_NETWORK_STATE</name>
      </permission>
    </permissions>
  </call>
  <call>
    <file>./smali/com/inoview/mplus/xml/webview/MyWebViewClient.java</file>
    <line>33</line>
    <permissions>
      <permission>
        <name>android.permission.ACCESS_NETWORK_STATE</name>
      </permission>
    </permissions>
  </call>
  <call>
    <file>./smali/android/support/v4/net/ConnectivityManagerCompat$JellyBeanConnectivityManagerCompatImpl.java</file>
    <line>76</line>
    <permissions/>
  </call>
  <call>
    <file>./smali/android/support/v4/net/ConnectivityManagerCompatJellyBean.java</file>
    <line>26</line>
    <permissions/>
  </call>
  <call>
    <file>./smali/android/support/v4/net/ConnectivityManagerCompat$GingerbreadConnectivityManagerCompatImpl.java</file>
    <line>61</line>
    <permissions/>
  </call>
  <call>
    <file>./smali/android/support/v4/net/ConnectivityManagerCompat$HoneycombMR2ConnectivityManagerCompatImpl.java</file>
    <line>69</line>
    <permissions/>
  </call>
  <call>
    <file>./smali/android/support/v4/net/ConnectivityManagerCompat.java</file>
    <line>102</line>
    <permissions/>
  </call>
  <call>
    <file>./smali/android/support/v4/net/ConnectivityManagerCompatGingerbread.java</file>
    <line>35</line>
    <permissions>
      <permission>
        <name>android.permission.ACCESS_NETWORK_STATE</name>
      </permission>
    </permissions>
  </call>
  <call>
    <file>./smali/android/support/v4/net/ConnectivityManagerCompat$BaseConnectivityManagerCompatImpl.java</file>
    <line>39</line>
    <permissions>
      <permission>
        <name>android.permission.ACCESS_NETWORK_STATE</name>
      </permission>
    </permissions>
  </call>
  <call>
    <file>./smali/android/support/v4/net/ConnectivityManagerCompatHoneycombMR2.java</file>
    <line>37</line>
    <permissions>
      <permission>
        <name>android.permission.ACCESS_NETWORK_STATE</name>
      </permission>
    </permissions>
  </call>
  <call>
    <file>./smali/android/support/v4/view/accessibility/AccessibilityNodeProviderCompat$AccessibilityNodeProviderJellyBeanImpl$1.java</file>
    <line>52</line>
    <permissions/>
  </call>
  <call>
    <file>./smali/android/support/v4/view/accessibility/AccessibilityNodeProviderCompatJellyBean$1.java</file>
    <line>55</line>
    <permissions/>
  </call>
  <call>
    <file>./smali/kr/or/kcie/tablet/FlashActivity.java</file>
    <line>45</line>
    <permissions>
      <permission>
        <name>android.permission.ACCESS_NETWORK_STATE</name>
      </permission>
    </permissions>
  </call>
  <call>
    <file>./smali/kr/or/kcie/tablet/MainActivity$WebViewClientClass.java</file>
    <line>194</line>
    <permissions>
      <permission>
        <name>android.permission.ACCESS_NETWORK_STATE</name>
      </permission>
    </permissions>
  </call>
  <call>
    <file>./smali/kr/or/kcie/tablet/MainActivity$4.java</file>
    <line>157</line>
    <permissions>
      <permission>
        <name>android.permission.ACCESS_NETWORK_STATE</name>
      </permission>
    </permissions>
  </call>
  <call>
    <file>./smali/kr/or/kcie/tablet/MainActivity$4.java</file>
    <line>158</line>
    <permissions>
      <permission>
        <name>android.permission.ACCESS_NETWORK_STATE</name>
      </permission>
    </permissions>
  </call>
  <call>
    <file>./smali/kr/or/kcie/tablet/MainActivity$4.java</file>
    <line>160</line>
    <permissions>
      <permission>
        <name>android.permission.ACCESS_NETWORK_STATE</name>
      </permission>
    </permissions>
  </call>
  <call>
    <file>./smali/kr/or/kcie/tablet/IntroActivity.java</file>
    <line>54</line>
    <permissions>
      <permission>
        <name>android.permission.INTERNET</name>
      </permission>
    </permissions>
  </call>
  <call>
    <file>./smali/kr/or/kcie/tablet/MainActivity$1.java</file>
    <line>97</line>
    <permissions>
      <permission>
        <name>android.permission.ACCESS_NETWORK_STATE</name>
      </permission>
    </permissions>
  </call>
  <call>
    <file>./smali/kr/or/kcie/tablet/MainActivity$1.java</file>
    <line>98</line>
    <permissions>
      <permission>
        <name>android.permission.ACCESS_NETWORK_STATE</name>
      </permission>
    </permissions>
  </call>
  <call>
    <file>./smali/kr/or/kcie/tablet/MainActivity$1.java</file>
    <line>100</line>
    <permissions>
      <permission>
        <name>android.permission.ACCESS_NETWORK_STATE</name>
      </permission>
    </permissions>
  </call>
  <call>
    <file>./smali/kr/or/kcie/tablet/FlashActivity$WebViewClientClass.java</file>
    <line>55</line>
    <permissions>
      <permission>
        <name>android.permission.ACCESS_NETWORK_STATE</name>
      </permission>
    </permissions>
  </call>
  <call>
    <file>./smali/kr/or/kcie/tablet/MainActivity$3.java</file>
    <line>144</line>
    <permissions>
      <permission>
        <name>android.permission.ACCESS_NETWORK_STATE</name>
      </permission>
    </permissions>
  </call>
  <call>
    <file>./smali/kr/or/kcie/tablet/AndroidBridge$3.java</file>
    <line>422</line>
    <permissions>
      <permission>
        <name>android.permission.ACCESS_NETWORK_STATE</name>
      </permission>
    </permissions>
  </call>
  <call>
    <file>./smali/kr/or/kcie/tablet/FlashActivity$1.java</file>
    <line>37</line>
    <permissions>
      <permission>
        <name>android.permission.ACCESS_NETWORK_STATE</name>
      </permission>
    </permissions>
  </call>
  <call>
    <file>./smali/kr/or/kcie/tablet/MainActivity.java</file>
    <line>177</line>
    <permissions>
      <permission>
        <name>android.permission.ACCESS_NETWORK_STATE</name>
      </permission>
    </permissions>
  </call>
  <call>
    <file>./smali/kr/or/kcie/tablet/MainActivity.java</file>
    <line>178</line>
    <permissions>
      <permission>
        <name>android.permission.ACCESS_NETWORK_STATE</name>
      </permission>
    </permissions>
  </call>
  <call>
    <file>./smali/kr/or/kcie/tablet/MainActivity.java</file>
    <line>182</line>
    <permissions>
      <permission>
        <name>android.permission.ACCESS_NETWORK_STATE</name>
      </permission>
    </permissions>
  </call>
  <call>
    <file>./smali/kr/or/kcie/tablet/MainActivity.java</file>
    <line>78</line>
    <permissions>
      <permission>
        <name>android.permission.ACCESS_NETWORK_STATE</name>
      </permission>
    </permissions>
  </call>
  <call>
    <file>./smali/kr/or/kcie/tablet/MainActivity.java</file>
    <line>80</line>
    <permissions>
      <permission>
        <name>android.permission.ACCESS_NETWORK_STATE</name>
      </permission>
    </permissions>
  </call>
  <call>
    <file>./smali/kr/or/kcie/tablet/MainActivity.java</file>
    <line>81</line>
    <permissions>
      <permission>
        <name>android.permission.ACCESS_NETWORK_STATE</name>
      </permission>
    </permissions>
  </call>
  <call>
    <file>./smali/kr/or/kcie/tablet/MainActivity.java</file>
    <line>83</line>
    <permissions>
      <permission>
        <name>android.permission.ACCESS_NETWORK_STATE</name>
      </permission>
    </permissions>
  </call>
  <call>
    <file>./smali/kr/or/kcie/tablet/MainActivity.java</file>
    <line>84</line>
    <permissions>
      <permission>
        <name>android.permission.ACCESS_NETWORK_STATE</name>
      </permission>
    </permissions>
  </call>
  <call>
    <file>./smali/org/apache/commons/io/input/XmlStreamReader.java</file>
    <line>241</line>
    <permissions>
      <permission>
        <name>android.permission.INTERNET</name>
      </permission>
    </permissions>
  </call>
  <call>
    <file>./smali/org/apache/commons/io/input/XmlStreamReader.java</file>
    <line>267</line>
    <permissions>
      <permission>
        <name>android.permission.INTERNET</name>
      </permission>
    </permissions>
  </call>
  <call>
    <file>./smali/org/apache/commons/io/FileUtils.java</file>
    <line>1460</line>
    <permissions>
      <permission>
        <name>android.permission.INTERNET</name>
      </permission>
    </permissions>
  </call>
  <call>
    <file>./smali/org/apache/commons/io/FileUtils.java</file>
    <line>1486</line>
    <permissions>
      <permission>
        <name>android.permission.INTERNET</name>
      </permission>
    </permissions>
  </call>
  <call>
    <file>./smali/org/apache/commons/io/FileUtils.java</file>
    <line>1489</line>
    <permissions>
      <permission>
        <name>android.permission.INTERNET</name>
      </permission>
    </permissions>
  </call>
  <call>
    <file>./smali/org/apache/commons/io/IOUtils.java</file>
    <line>633</line>
    <permissions>
      <permission>
        <name>android.permission.INTERNET</name>
      </permission>
    </permissions>
  </call>
  <call>
    <file>./smali/org/apache/commons/io/IOUtils.java</file>
    <line>654</line>
    <permissions>
      <permission>
        <name>android.permission.INTERNET</name>
      </permission>
    </permissions>
  </call>
  <call>
    <file>./smali/org/apache/commons/io/IOUtils.java</file>
    <line>894</line>
    <permissions>
      <permission>
        <name>android.permission.INTERNET</name>
      </permission>
    </permissions>
  </call>
</calls>
