<?xml version="1.0"?>
<calls>
  <call>
    <file>./smali/g.java</file>
    <line>0</line>
    <permissions>
      <permission>
        <name>android.permission.INTERNET</name>
      </permission>
    </permissions>
  </call>
  <call>
    <file>./smali/a.java</file>
    <line>0</line>
    <permissions/>
  </call>
  <call>
    <file>./smali/w.java</file>
    <line>0</line>
    <permissions>
      <permission>
        <name>android.permission.INTERNET</name>
      </permission>
    </permissions>
  </call>
  <call>
    <file>./smali/w.java</file>
    <line>0</line>
    <permissions>
      <permission>
        <name>android.permission.INTERNET</name>
      </permission>
    </permissions>
  </call>
  <call>
    <file>./smali/com/pskpartha/cityguide/MapViewActivity.java</file>
    <line>67</line>
    <permissions/>
  </call>
  <call>
    <file>./smali/com/pskpartha/cityguide/MapViewActivity.java</file>
    <line>54</line>
    <permissions/>
  </call>
  <call>
    <file>./smali/com/pskpartha/cityguide/FacebookActivity$HelloWebViewClient.java</file>
    <line>43</line>
    <permissions/>
  </call>
  <call>
    <file>./smali/com/pskpartha/cityguide/CityGuideActivity.java</file>
    <line>66</line>
    <permissions>
      <permission>
        <name>android.permission.ACCESS_FINE_LOCATION</name>
      </permission>
      <permission>
        <name>android.permission.ACCESS_COARSE_LOCATION</name>
      </permission>
    </permissions>
  </call>
  <call>
    <file>./smali/com/pskpartha/cityguide/CityGuideActivity.java</file>
    <line>100</line>
    <permissions>
      <permission>
        <name>android.permission.ACCESS_FINE_LOCATION</name>
      </permission>
      <permission>
        <name>android.permission.ACCESS_COARSE_LOCATION</name>
      </permission>
    </permissions>
  </call>
  <call>
    <file>./smali/com/pskpartha/cityguide/TwitterActivity$HelloWebViewClient.java</file>
    <line>43</line>
    <permissions/>
  </call>
  <call>
    <file>./smali/com/pskpartha/cityguide/TwitterActivity.java</file>
    <line>64</line>
    <permissions/>
  </call>
  <call>
    <file>./smali/com/pskpartha/cityguide/TwitterActivity.java</file>
    <line>51</line>
    <permissions/>
  </call>
  <call>
    <file>./smali/com/pskpartha/cityguide/MapViewActivity$HelloWebViewClient.java</file>
    <line>46</line>
    <permissions/>
  </call>
  <call>
    <file>./smali/com/pskpartha/cityguide/FacebookActivity.java</file>
    <line>64</line>
    <permissions/>
  </call>
  <call>
    <file>./smali/com/pskpartha/cityguide/FacebookActivity.java</file>
    <line>51</line>
    <permissions/>
  </call>
  <call>
    <file>./smali/com/pskpartha/cityguide/extra/CacheImageDownloader$BitmapDownloaderTask.java</file>
    <line>288</line>
    <permissions>
      <permission>
        <name>android.permission.INTERNET</name>
      </permission>
    </permissions>
  </call>
  <call>
    <file>./smali/com/pskpartha/cityguide/extra/SharedPreferencesHelper.java</file>
    <line>169</line>
    <permissions>
      <permission>
        <name>android.permission.ACCESS_NETWORK_STATE</name>
      </permission>
    </permissions>
  </call>
  <call>
    <file>./smali/com/pskpartha/cityguide/extra/PskHttpRequest.java</file>
    <line>186</line>
    <permissions>
      <permission>
        <name>android.permission.INTERNET</name>
      </permission>
    </permissions>
  </call>
  <call>
    <file>./smali/com/pskpartha/cityguide/extra/PskHttpRequest.java</file>
    <line>222</line>
    <permissions>
      <permission>
        <name>android.permission.INTERNET</name>
      </permission>
    </permissions>
  </call>
  <call>
    <file>./smali/com/google/ads/AdActivity.java</file>
    <line>141</line>
    <permissions>
      <permission>
        <name>android.permission.WAKE_LOCK</name>
      </permission>
    </permissions>
  </call>
  <call>
    <file>./smali/com/google/ads/util/AdUtil.java</file>
    <line>141</line>
    <permissions>
      <permission>
        <name>android.permission.ACCESS_NETWORK_STATE</name>
      </permission>
    </permissions>
  </call>
  <call>
    <file>./smali/com/google/ads/util/AdUtil.java</file>
    <line>141</line>
    <permissions>
      <permission>
        <name>android.permission.INTERNET</name>
      </permission>
    </permissions>
  </call>
  <call>
    <file>./smali/com/google/ads/InstallReceiver.java</file>
    <line>141</line>
    <permissions>
      <permission>
        <name>android.permission.INTERNET</name>
      </permission>
    </permissions>
  </call>
  <call>
    <file>./smali/c.java</file>
    <line>141</line>
    <permissions>
      <permission>
        <name>android.permission.INTERNET</name>
      </permission>
    </permissions>
  </call>
  <call>
    <file>./smali/c.java</file>
    <line>141</line>
    <permissions/>
  </call>
  <call>
    <file>./smali/c.java</file>
    <line>141</line>
    <permissions/>
  </call>
  <call>
    <file>./smali/c.java</file>
    <line>141</line>
    <permissions/>
  </call>
  <call>
    <file>./smali/c.java</file>
    <line>141</line>
    <permissions/>
  </call>
  <call>
    <file>./smali/c.java</file>
    <line>141</line>
    <permissions/>
  </call>
  <call>
    <file>./smali/c.java</file>
    <line>141</line>
    <permissions/>
  </call>
  <call>
    <file>./smali/v.java</file>
    <line>141</line>
    <permissions>
      <permission>
        <name>android.permission.WAKE_LOCK</name>
      </permission>
    </permissions>
  </call>
  <call>
    <file>./smali/v.java</file>
    <line>141</line>
    <permissions>
      <permission>
        <name>android.permission.WAKE_LOCK</name>
      </permission>
    </permissions>
  </call>
  <call>
    <file>./smali/v.java</file>
    <line>141</line>
    <permissions/>
  </call>
  <call>
    <file>./smali/v.java</file>
    <line>141</line>
    <permissions>
      <permission>
        <name>android.permission.WAKE_LOCK</name>
      </permission>
    </permissions>
  </call>
  <call>
    <file>./smali/v.java</file>
    <line>141</line>
    <permissions>
      <permission>
        <name>android.permission.WAKE_LOCK</name>
      </permission>
    </permissions>
  </call>
  <call>
    <file>./smali/v.java</file>
    <line>141</line>
    <permissions>
      <permission>
        <name>android.permission.WAKE_LOCK</name>
      </permission>
    </permissions>
  </call>
  <call>
    <file>./smali/b.java</file>
    <line>141</line>
    <permissions>
      <permission>
        <name>android.permission.INTERNET</name>
      </permission>
    </permissions>
  </call>
  <call>
    <file>./smali/b.java</file>
    <line>141</line>
    <permissions>
      <permission>
        <name>android.permission.INTERNET</name>
      </permission>
    </permissions>
  </call>
</calls>
