<apicalls>
<call>
<permissions>
<permission>
<name>android.permission.ACCESS_NETWORK_STATE</name>
<apiversion>2.2.3</apiversion>
<apiversion>2.3.6</apiversion>
<apiversion>3.2.2</apiversion>
</permission>
</permissions>
<file>./smali/com/startapp/android/publish/d/b$1$2.java</file>
<line></line>
<protected>android/webkit/WebView;-$gt;destroy</protected>
<deleted>false</deleted>
</call>
<call>
<permissions>
<permission>
<name>android.permission.INTERNET</name>
<apiversion>4.1.1</apiversion>
<apiversion>2.2.3</apiversion>
<apiversion>2.3.6</apiversion>
<apiversion>3.2.2</apiversion>
<apiversion>4.0.1</apiversion>
</permission>
</permissions>
<file>./smali/com/startapp/android/publish/d/b.java</file>
<line></line>
<protected>android/webkit/WebView;-$gt;$lt;init$gt;</protected>
<deleted>false</deleted>
</call>
<call>
<permissions>
<permission>
<name>android.permission.ACCESS_NETWORK_STATE</name>
<apiversion>2.2.3</apiversion>
<apiversion>2.3.6</apiversion>
<apiversion>3.2.2</apiversion>
</permission>
</permissions>
<file>./smali/com/startapp/android/publish/d/b$2.java</file>
<line></line>
<protected>android/webkit/WebView;-$gt;destroy</protected>
<deleted>false</deleted>
</call>
<call>
<permissions>
<permission>
<name>android.permission.ACCESS_NETWORK_STATE</name>
<apiversion>2.2.3</apiversion>
<apiversion>2.3.6</apiversion>
<apiversion>3.2.2</apiversion>
</permission>
</permissions>
<file>./smali/com/startapp/android/publish/list3d/List3DActivity.java</file>
<line></line>
<protected>android/webkit/WebView;-$gt;stopLoading</protected>
<deleted>false</deleted>
</call>
<call>
<permissions>
<permission>
<name>android.permission.ACCESS_NETWORK_STATE</name>
<apiversion>2.2.3</apiversion>
<apiversion>2.3.6</apiversion>
<apiversion>3.2.2</apiversion>
</permission>
</permissions>
<file>./smali/com/startapp/android/publish/AppWallDelegateActivity$a.java</file>
<line></line>
<protected>android/webkit/WebView;-$gt;destroy</protected>
<deleted>false</deleted>
</call>
<call>
<permissions>
<permission>
<name>android.permission.ACCESS_NETWORK_STATE</name>
<apiversion>2.2.3</apiversion>
<apiversion>2.3.6</apiversion>
<apiversion>3.2.2</apiversion>
</permission>
</permissions>
<file>./smali/com/startapp/android/publish/slider/b$a.java</file>
<line></line>
<protected>android/webkit/WebView;-$gt;loadUrl</protected>
<deleted>false</deleted>
</call>
<call>
<permissions>
<permission>
<name>android.permission.ACCESS_NETWORK_STATE</name>
<apiversion>2.2.3</apiversion>
<apiversion>2.3.6</apiversion>
<apiversion>3.2.2</apiversion>
</permission>
</permissions>
<file>./smali/com/startapp/android/publish/slider/b.java</file>
<line></line>
<protected>android/webkit/WebView;-$gt;addJavascriptInterface</protected>
<deleted>false</deleted>
</call>
<call>
<permissions>
<permission>
<name>android.permission.ACCESS_NETWORK_STATE</name>
<apiversion>2.2.3</apiversion>
<apiversion>2.3.6</apiversion>
<apiversion>3.2.2</apiversion>
</permission>
</permissions>
<file>./smali/com/startapp/android/publish/slider/b.java</file>
<line></line>
<protected>android/webkit/WebView;-$gt;loadUrl</protected>
<deleted>false</deleted>
</call>
<call>
<permissions>
<permission>
<name>android.permission.ACCESS_NETWORK_STATE</name>
<apiversion>2.2.3</apiversion>
<apiversion>2.3.6</apiversion>
<apiversion>3.2.2</apiversion>
</permission>
</permissions>
<file>./smali/com/startapp/android/publish/slider/b.java</file>
<line></line>
<protected>android/webkit/WebView;-$gt;loadUrl</protected>
<deleted>false</deleted>
</call>
<call>
<permissions>
<permission>
<name>android.permission.INTERNET</name>
<apiversion>4.1.1</apiversion>
<apiversion>2.2.3</apiversion>
<apiversion>2.3.6</apiversion>
<apiversion>3.2.2</apiversion>
<apiversion>4.0.1</apiversion>
</permission>
</permissions>
<file>./smali/com/startapp/android/publish/slider/b$2.java</file>
<line></line>
<protected>android/webkit/WebView;-$gt;$lt;init$gt;</protected>
<deleted>false</deleted>
</call>
<call>
<permissions>
<permission>
<name>android.permission.ACCESS_NETWORK_STATE</name>
<apiversion>2.2.3</apiversion>
<apiversion>2.3.6</apiversion>
<apiversion>3.2.2</apiversion>
</permission>
<permission>
<name>android.permission.WAKE_LOCK</name>
<apiversion>3.2.2</apiversion>
<apiversion>4.0.1</apiversion>
</permission>
</permissions>
<file>./smali/com/startapp/android/publish/slider/b$2.java</file>
<line></line>
<protected>android/webkit/WebView;-$gt;onKeyDown</protected>
<deleted>false</deleted>
</call>
<call>
<permissions>
<permission>
<name>android.permission.ACCESS_NETWORK_STATE</name>
<apiversion>2.2.3</apiversion>
<apiversion>2.3.6</apiversion>
<apiversion>3.2.2</apiversion>
</permission>
</permissions>
<file>./smali/com/startapp/android/publish/slider/b$2.java</file>
<line></line>
<protected>android/webkit/WebView;-$gt;goBack</protected>
<deleted>false</deleted>
</call>
<call>
<permissions>
<permission>
<name>android.permission.ACCESS_NETWORK_STATE</name>
<apiversion>2.2.3</apiversion>
<apiversion>2.3.6</apiversion>
<apiversion>3.2.2</apiversion>
</permission>
</permissions>
<file>./smali/com/startapp/android/publish/slider/b$a$1.java</file>
<line></line>
<protected>android/webkit/WebView;-$gt;loadUrl</protected>
<deleted>false</deleted>
</call>
<call>
<permissions>
<permission>
<name>android.permission.ACCESS_NETWORK_STATE</name>
<apiversion>2.2.3</apiversion>
<apiversion>2.3.6</apiversion>
<apiversion>3.2.2</apiversion>
</permission>
</permissions>
<file>./smali/com/startapp/android/publish/adinformation/a.java</file>
<line></line>
<protected>android/webkit/WebView;-$gt;loadUrl</protected>
<deleted>false</deleted>
</call>
<call>
<permissions>
<permission>
<name>android.permission.INTERNET</name>
<apiversion>4.1.1</apiversion>
<apiversion>2.2.3</apiversion>
<apiversion>2.3.6</apiversion>
<apiversion>3.2.2</apiversion>
<apiversion>4.0.1</apiversion>
</permission>
</permissions>
<file>./smali/com/startapp/android/publish/adinformation/a.java</file>
<line></line>
<protected>android/webkit/WebView;-$gt;$lt;init$gt;</protected>
<deleted>false</deleted>
</call>
<call>
<permissions>
<permission>
<name>android.permission.ACCESS_NETWORK_STATE</name>
<apiversion>2.2.3</apiversion>
<apiversion>2.3.6</apiversion>
<apiversion>3.2.2</apiversion>
</permission>
</permissions>
<file>./smali/com/startapp/android/publish/adinformation/a.java</file>
<line></line>
<protected>android/webkit/WebView;-$gt;loadUrl</protected>
<deleted>false</deleted>
</call>
<call>
<permissions>
<permission>
<name>android.permission.ACCESS_NETWORK_STATE</name>
<apiversion>2.2.3</apiversion>
<apiversion>2.3.6</apiversion>
<apiversion>3.2.2</apiversion>
</permission>
</permissions>
<file>./smali/com/startapp/android/publish/adinformation/a.java</file>
<line></line>
<protected>android/webkit/WebView;-$gt;addJavascriptInterface</protected>
<deleted>false</deleted>
</call>
<call>
<permissions>
<permission>
<name>android.permission.INTERNET</name>
<apiversion>4.1.1</apiversion>
<apiversion>2.2.3</apiversion>
<apiversion>2.3.6</apiversion>
<apiversion>3.2.2</apiversion>
<apiversion>4.0.1</apiversion>
</permission>
</permissions>
<file>./smali/com/startapp/android/publish/banner/bannerstandard/BannerStandard.java</file>
<line></line>
<protected>android/webkit/WebView;-$gt;$lt;init$gt;</protected>
<deleted>false</deleted>
</call>
<call>
<permissions>
<permission>
<name>android.permission.ACCESS_NETWORK_STATE</name>
<apiversion>2.2.3</apiversion>
<apiversion>2.3.6</apiversion>
<apiversion>3.2.2</apiversion>
</permission>
</permissions>
<file>./smali/com/startapp/android/publish/banner/bannerstandard/BannerStandard.java</file>
<line></line>
<protected>android/webkit/WebView;-$gt;setBackgroundColor</protected>
<deleted>false</deleted>
</call>
<call>
<permissions>
<permission>
<name>android.permission.ACCESS_NETWORK_STATE</name>
<apiversion>2.2.3</apiversion>
<apiversion>2.3.6</apiversion>
<apiversion>3.2.2</apiversion>
</permission>
</permissions>
<file>./smali/com/startapp/android/publish/banner/bannerstandard/BannerStandard$MyWebViewClient.java</file>
<line></line>
<protected>android/webkit/WebView;-$gt;stopLoading</protected>
<deleted>false</deleted>
</call>
<call>
<permissions>
<permission>
<name>android.permission.ACCESS_NETWORK_STATE</name>
<apiversion>2.2.3</apiversion>
<apiversion>2.3.6</apiversion>
<apiversion>3.2.2</apiversion>
</permission>
</permissions>
<file>./smali/com/startapp/android/publish/banner/bannerstandard/BannerStandard$3.java</file>
<line></line>
<protected>android/webkit/WebView;-$gt;addJavascriptInterface</protected>
<deleted>false</deleted>
</call>
<call>
<permissions>
<permission>
<name>android.permission.INTERNET</name>
<apiversion>4.1.1</apiversion>
<apiversion>2.2.3</apiversion>
<apiversion>2.3.6</apiversion>
<apiversion>3.2.2</apiversion>
<apiversion>4.0.1</apiversion>
</permission>
</permissions>
<file>./smali/com/startapp/android/publish/Ad.java</file>
<line></line>
<protected>android/webkit/WebView;-$gt;$lt;init$gt;</protected>
<deleted>false</deleted>
</call>
<call>
<permissions>
<permission>
<name>android.permission.ACCESS_NETWORK_STATE</name>
<apiversion>4.1.1</apiversion>
<apiversion>2.2.3</apiversion>
<apiversion>2.3.6</apiversion>
<apiversion>3.2.2</apiversion>
<apiversion>4.0.1</apiversion>
</permission>
</permissions>
<file>./smali/com/startapp/android/publish/g/l.java</file>
<line></line>
<protected>android/net/ConnectivityManager;-$gt;getActiveNetworkInfo</protected>
<deleted>false</deleted>
</call>
<call>
<permissions>
<permission>
<name>android.permission.INTERNET</name>
<apiversion>4.1.1</apiversion>
<apiversion>2.2.3</apiversion>
<apiversion>2.3.6</apiversion>
<apiversion>3.2.2</apiversion>
<apiversion>4.0.1</apiversion>
</permission>
</permissions>
<file>./smali/com/startapp/android/publish/g/l.java</file>
<line></line>
<protected>java/net/URL;-$gt;openConnection</protected>
<deleted>false</deleted>
</call>
<call>
<permissions>
<permission>
<name>android.permission.ACCESS_NETWORK_STATE</name>
<apiversion>4.1.1</apiversion>
<apiversion>2.2.3</apiversion>
<apiversion>2.3.6</apiversion>
<apiversion>3.2.2</apiversion>
<apiversion>4.0.1</apiversion>
</permission>
</permissions>
<file>./smali/com/startapp/android/publish/g/l.java</file>
<line></line>
<protected>android/net/ConnectivityManager;-$gt;getActiveNetworkInfo</protected>
<deleted>false</deleted>
</call>
<call>
<permissions>
<permission>
<name>android.permission.ACCESS_WIFI_STATE</name>
<apiversion>4.1.1</apiversion>
<apiversion>2.2.3</apiversion>
<apiversion>2.3.6</apiversion>
<apiversion>3.2.2</apiversion>
<apiversion>4.0.1</apiversion>
</permission>
</permissions>
<file>./smali/com/startapp/android/publish/g/l.java</file>
<line></line>
<protected>android/net/wifi/WifiManager;-$gt;getConnectionInfo</protected>
<deleted>false</deleted>
</call>
<call>
<permissions>
<permission>
<name>android.permission.INTERNET</name>
<apiversion>4.1.1</apiversion>
<apiversion>2.2.3</apiversion>
<apiversion>2.3.6</apiversion>
<apiversion>3.2.2</apiversion>
<apiversion>4.0.1</apiversion>
</permission>
</permissions>
<file>./smali/com/startapp/android/publish/g/g.java</file>
<line></line>
<protected>java/net/URL;-$gt;openConnection</protected>
<deleted>false</deleted>
</call>
<call>
<permissions>
<permission>
<name>android.permission.INTERNET</name>
<apiversion>4.1.1</apiversion>
<apiversion>2.2.3</apiversion>
<apiversion>2.3.6</apiversion>
<apiversion>3.2.2</apiversion>
<apiversion>4.0.1</apiversion>
</permission>
</permissions>
<file>./smali/com/startapp/android/publish/g/g.java</file>
<line></line>
<protected>java/net/HttpURLConnection;-$gt;connect</protected>
<deleted>false</deleted>
</call>
<call>
<permissions>
<permission>
<name>android.permission.ACCESS_NETWORK_STATE</name>
<apiversion>2.2.3</apiversion>
<apiversion>2.3.6</apiversion>
<apiversion>3.2.2</apiversion>
</permission>
</permissions>
<file>./smali/com/startapp/android/publish/g/r$2.java</file>
<line></line>
<protected>android/webkit/WebView;-$gt;stopLoading</protected>
<deleted>false</deleted>
</call>
<call>
<permissions>
<permission>
<name>android.permission.INTERNET</name>
<apiversion>4.1.1</apiversion>
<apiversion>2.2.3</apiversion>
<apiversion>2.3.6</apiversion>
<apiversion>3.2.2</apiversion>
<apiversion>4.0.1</apiversion>
</permission>
</permissions>
<file>./smali/com/startapp/android/publish/g/r.java</file>
<line></line>
<protected>android/webkit/WebView;-$gt;$lt;init$gt;</protected>
<deleted>false</deleted>
</call>
<call>
<permissions>
<permission>
<name>android.permission.ACCESS_NETWORK_STATE</name>
<apiversion>2.2.3</apiversion>
<apiversion>2.3.6</apiversion>
<apiversion>3.2.2</apiversion>
</permission>
</permissions>
<file>./smali/com/startapp/android/publish/g/r.java</file>
<line></line>
<protected>android/webkit/WebView;-$gt;loadUrl</protected>
<deleted>false</deleted>
</call>
<call>
<permissions>
<permission>
<name>android.permission.ACCESS_NETWORK_STATE</name>
<apiversion>2.2.3</apiversion>
<apiversion>2.3.6</apiversion>
<apiversion>3.2.2</apiversion>
</permission>
</permissions>
<file>./smali/com/startapp/android/publish/g/r.java</file>
<line></line>
<protected>android/webkit/WebView;-$gt;loadData</protected>
<deleted>false</deleted>
</call>
<call>
<permissions>
<permission>
<name>android.permission.ACCESS_NETWORK_STATE</name>
<apiversion>2.2.3</apiversion>
<apiversion>2.3.6</apiversion>
<apiversion>3.2.2</apiversion>
</permission>
</permissions>
<file>./smali/com/startapp/android/publish/g/r.java</file>
<line></line>
<protected>android/webkit/WebView;-$gt;loadDataWithBaseURL</protected>
<deleted>false</deleted>
</call>
<call>
<permissions>
<permission>
<name>android.permission.ACCESS_NETWORK_STATE</name>
<apiversion>4.1.1</apiversion>
<apiversion>2.2.3</apiversion>
<apiversion>2.3.6</apiversion>
<apiversion>3.2.2</apiversion>
<apiversion>4.0.1</apiversion>
</permission>
</permissions>
<file>./smali/com/startapp/android/publish/g/r.java</file>
<line></line>
<protected>android/net/ConnectivityManager;-$gt;getActiveNetworkInfo</protected>
<deleted>false</deleted>
</call>
<call>
<permissions>
<permission>
<name>android.permission.READ_PHONE_STATE</name>
<apiversion>4.1.1</apiversion>
<apiversion>2.2.3</apiversion>
<apiversion>2.3.6</apiversion>
<apiversion>3.2.2</apiversion>
<apiversion>4.0.1</apiversion>
</permission>
<permission>
<name>android.permission.ACCESS_COARSE_LOCATION</name>
<apiversion>4.1.1</apiversion>
<apiversion>2.2.3</apiversion>
<apiversion>2.3.6</apiversion>
<apiversion>3.2.2</apiversion>
<apiversion>4.0.1</apiversion>
</permission>
</permissions>
<file>./smali/com/startapp/android/publish/g/k.java</file>
<line></line>
<protected>android/telephony/TelephonyManager;-$gt;listen</protected>
<deleted>false</deleted>
</call>
<call>
<permissions>
<permission>
<name>android.permission.INTERNET</name>
<apiversion>4.1.1</apiversion>
<apiversion>2.2.3</apiversion>
<apiversion>2.3.6</apiversion>
<apiversion>3.2.2</apiversion>
<apiversion>4.0.1</apiversion>
</permission>
</permissions>
<file>./smali/com/startapp/android/publish/splash/b.java</file>
<line></line>
<protected>android/webkit/WebView;-$gt;$lt;init$gt;</protected>
<deleted>false</deleted>
</call>
<call>
<permissions>
<permission>
<name>android.permission.ACCESS_NETWORK_STATE</name>
<apiversion>2.2.3</apiversion>
<apiversion>2.3.6</apiversion>
<apiversion>3.2.2</apiversion>
</permission>
</permissions>
<file>./smali/com/startapp/android/publish/splash/b.java</file>
<line></line>
<protected>android/webkit/WebView;-$gt;setBackgroundColor</protected>
<deleted>false</deleted>
</call>
<call>
<permissions>
<permission>
<name>android.permission.ACCESS_NETWORK_STATE</name>
<apiversion>2.2.3</apiversion>
<apiversion>2.3.6</apiversion>
<apiversion>3.2.2</apiversion>
</permission>
</permissions>
<file>./smali/com/startapp/android/publish/splash/b.java</file>
<line></line>
<protected>android/webkit/WebView;-$gt;loadUrl</protected>
<deleted>false</deleted>
</call>
<call>
<permissions>
<permission>
<name>android.permission.ACCESS_NETWORK_STATE</name>
<apiversion>2.2.3</apiversion>
<apiversion>2.3.6</apiversion>
<apiversion>3.2.2</apiversion>
</permission>
</permissions>
<file>./smali/com/startapp/android/publish/c/e.java</file>
<line></line>
<protected>android/webkit/WebView;-$gt;setBackgroundColor</protected>
<deleted>false</deleted>
</call>
<call>
<permissions>
<permission>
<name>android.permission.ACCESS_NETWORK_STATE</name>
<apiversion>2.2.3</apiversion>
<apiversion>2.3.6</apiversion>
<apiversion>3.2.2</apiversion>
</permission>
</permissions>
<file>./smali/com/startapp/android/publish/c/e$1.java</file>
<line></line>
<protected>android/webkit/WebView;-$gt;setBackgroundColor</protected>
<deleted>false</deleted>
</call>
<call>
<permissions>
<permission>
<name>android.permission.INTERNET</name>
<apiversion>4.1.1</apiversion>
<apiversion>2.2.3</apiversion>
<apiversion>2.3.6</apiversion>
<apiversion>3.2.2</apiversion>
<apiversion>4.0.1</apiversion>
</permission>
</permissions>
<file>./smali/com/startapp/android/publish/c/c.java</file>
<line></line>
<protected>android/webkit/WebView;-$gt;$lt;init$gt;</protected>
<deleted>false</deleted>
</call>
<call>
<permissions>
<permission>
<name>android.permission.ACCESS_NETWORK_STATE</name>
<apiversion>2.2.3</apiversion>
<apiversion>2.3.6</apiversion>
<apiversion>3.2.2</apiversion>
</permission>
</permissions>
<file>./smali/com/startapp/android/publish/c/c.java</file>
<line></line>
<protected>android/webkit/WebView;-$gt;setBackgroundColor</protected>
<deleted>false</deleted>
</call>
<call>
<permissions>
<permission>
<name>android.permission.ACCESS_NETWORK_STATE</name>
<apiversion>2.2.3</apiversion>
<apiversion>2.3.6</apiversion>
<apiversion>3.2.2</apiversion>
</permission>
</permissions>
<file>./smali/com/startapp/android/publish/c/c.java</file>
<line></line>
<protected>android/webkit/WebView;-$gt;addJavascriptInterface</protected>
<deleted>false</deleted>
</call>
<call>
<permissions>
<permission>
<name>android.permission.ACCESS_NETWORK_STATE</name>
<apiversion>2.2.3</apiversion>
<apiversion>2.3.6</apiversion>
<apiversion>3.2.2</apiversion>
</permission>
</permissions>
<file>./smali/com/startapp/android/publish/c/c$b.java</file>
<line></line>
<protected>android/webkit/WebView;-$gt;loadUrl</protected>
<deleted>false</deleted>
</call>
<call>
<permissions>
<permission>
<name>android.permission.INTERNET</name>
<apiversion>4.1.1</apiversion>
<apiversion>2.2.3</apiversion>
<apiversion>2.3.6</apiversion>
<apiversion>3.2.2</apiversion>
<apiversion>4.0.1</apiversion>
</permission>
</permissions>
<file>./smali/com/startapp/android/publish/AppWallDelegateActivity.java</file>
<line></line>
<protected>android/webkit/WebView;-$gt;$lt;init$gt;</protected>
<deleted>false</deleted>
</call>
<call>
<permissions>
<permission>
<name>android.permission.ACCESS_NETWORK_STATE</name>
<apiversion>2.2.3</apiversion>
<apiversion>2.3.6</apiversion>
<apiversion>3.2.2</apiversion>
</permission>
</permissions>
<file>./smali/com/startapp/android/publish/AppWallDelegateActivity.java</file>
<line></line>
<protected>android/webkit/WebView;-$gt;loadUrl</protected>
<deleted>false</deleted>
</call>
<call>
<permissions>
<permission>
<name>android.permission.INTERNET</name>
<apiversion>4.1.1</apiversion>
<apiversion>2.2.3</apiversion>
<apiversion>2.3.6</apiversion>
<apiversion>3.2.2</apiversion>
<apiversion>4.0.1</apiversion>
</permission>
</permissions>
<file>./smali/com/google/android/gms/a/l.java</file>
<line></line>
<protected>org/apache/http/impl/client/DefaultHttpClient;-$gt;$lt;init$gt;</protected>
<deleted>false</deleted>
</call>
<call>
<permissions>
<permission>
<name>android.permission.ACCESS_NETWORK_STATE</name>
<apiversion>4.1.1</apiversion>
<apiversion>2.2.3</apiversion>
<apiversion>2.3.6</apiversion>
<apiversion>3.2.2</apiversion>
<apiversion>4.0.1</apiversion>
</permission>
</permissions>
<file>./smali/com/google/android/gms/a/q.java</file>
<line></line>
<protected>android/net/ConnectivityManager;-$gt;getActiveNetworkInfo</protected>
<deleted>false</deleted>
</call>
<call>
<permissions>
<permission>
<name>android.permission.INTERNET</name>
<apiversion>4.1.1</apiversion>
<apiversion>2.2.3</apiversion>
<apiversion>2.3.6</apiversion>
<apiversion>3.2.2</apiversion>
<apiversion>4.0.1</apiversion>
</permission>
</permissions>
<file>./smali/com/google/android/gms/internal/dy.java</file>
<line></line>
<protected>android/webkit/WebView;-$gt;$lt;init$gt;</protected>
<deleted>false</deleted>
</call>
<call>
<permissions>
<permission>
<name>android.permission.ACCESS_NETWORK_STATE</name>
<apiversion>4.1.1</apiversion>
</permission>
</permissions>
<file>./smali/com/google/android/gms/internal/da.java</file>
<line></line>
<protected>android/net/ConnectivityManager;-$gt;isActiveNetworkMetered</protected>
<deleted>false</deleted>
</call>
<call>
<permissions>
<permission>
<name>android.permission.ACCESS_NETWORK_STATE</name>
<apiversion>4.1.1</apiversion>
<apiversion>2.2.3</apiversion>
<apiversion>2.3.6</apiversion>
<apiversion>3.2.2</apiversion>
<apiversion>4.0.1</apiversion>
</permission>
</permissions>
<file>./smali/com/google/android/gms/internal/da.java</file>
<line></line>
<protected>android/net/ConnectivityManager;-$gt;getActiveNetworkInfo</protected>
<deleted>false</deleted>
</call>
<call>
<permissions>
<permission>
<name>android.permission.ACCESS_NETWORK_STATE</name>
<apiversion>4.1.1</apiversion>
<apiversion>2.2.3</apiversion>
<apiversion>2.3.6</apiversion>
<apiversion>3.2.2</apiversion>
<apiversion>4.0.1</apiversion>
</permission>
</permissions>
<file>./smali/com/google/android/gms/internal/da.java</file>
<line></line>
<protected>android/net/ConnectivityManager;-$gt;getActiveNetworkInfo</protected>
<deleted>false</deleted>
</call>
<call>
<permissions>
<permission>
<name>android.permission.ACCESS_NETWORK_STATE</name>
<apiversion>4.1.1</apiversion>
<apiversion>2.2.3</apiversion>
<apiversion>2.3.6</apiversion>
<apiversion>3.2.2</apiversion>
<apiversion>4.0.1</apiversion>
</permission>
</permissions>
<file>./smali/com/google/android/gms/internal/da.java</file>
<line></line>
<protected>android/net/ConnectivityManager;-$gt;getActiveNetworkInfo</protected>
<deleted>false</deleted>
</call>
<call>
<permissions>
<permission>
<name>android.permission.INTERNET</name>
<apiversion>4.1.1</apiversion>
<apiversion>2.2.3</apiversion>
<apiversion>2.3.6</apiversion>
<apiversion>3.2.2</apiversion>
<apiversion>4.0.1</apiversion>
</permission>
</permissions>
<file>./smali/com/google/android/gms/internal/cu.java</file>
<line></line>
<protected>java/net/URL;-$gt;openConnection</protected>
<deleted>false</deleted>
</call>
<call>
<permissions>
<permission>
<name>android.permission.INTERNET</name>
<apiversion>4.1.1</apiversion>
<apiversion>2.2.3</apiversion>
<apiversion>2.3.6</apiversion>
<apiversion>3.2.2</apiversion>
<apiversion>4.0.1</apiversion>
</permission>
</permissions>
<file>./smali/com/google/android/gms/internal/dw.java</file>
<line></line>
<protected>android/webkit/WebView;-$gt;$lt;init$gt;</protected>
<deleted>false</deleted>
</call>
<call>
<permissions>
<permission>
<name>android.permission.ACCESS_NETWORK_STATE</name>
<apiversion>2.2.3</apiversion>
<apiversion>2.3.6</apiversion>
<apiversion>3.2.2</apiversion>
</permission>
</permissions>
<file>./smali/com/google/android/gms/internal/dw.java</file>
<line></line>
<protected>android/webkit/WebView;-$gt;destroy</protected>
<deleted>false</deleted>
</call>
<call>
<permissions>
<permission>
<name>android.permission.ACCESS_NETWORK_STATE</name>
<apiversion>2.2.3</apiversion>
<apiversion>2.3.6</apiversion>
<apiversion>3.2.2</apiversion>
</permission>
<permission>
<name>android.permission.WAKE_LOCK</name>
<apiversion>3.2.2</apiversion>
</permission>
</permissions>
<file>./smali/com/google/android/gms/internal/dw.java</file>
<line></line>
<protected>android/webkit/WebView;-$gt;onTouchEvent</protected>
<deleted>false</deleted>
</call>
<call>
<permissions>
<permission>
<name>android.permission.INTERNET</name>
<apiversion>4.1.1</apiversion>
<apiversion>2.2.3</apiversion>
<apiversion>2.3.6</apiversion>
<apiversion>3.2.2</apiversion>
<apiversion>4.0.1</apiversion>
</permission>
</permissions>
<file>./smali/com/google/android/gms/internal/dq.java</file>
<line></line>
<protected>java/net/URL;-$gt;openConnection</protected>
<deleted>false</deleted>
</call>
<call>
<permissions>
<permission>
<name>android.permission.INTERNET</name>
<apiversion>4.1.1</apiversion>
<apiversion>2.2.3</apiversion>
<apiversion>2.3.6</apiversion>
<apiversion>3.2.2</apiversion>
<apiversion>4.0.1</apiversion>
</permission>
</permissions>
<file>./smali/com/google/android/gms/internal/dm.java</file>
<line></line>
<protected>android/webkit/WebView;-$gt;$lt;init$gt;</protected>
<deleted>false</deleted>
</call>
<call>
<permissions>
<permission>
<name>android.permission.ACCESS_NETWORK_STATE</name>
<apiversion>2.2.3</apiversion>
<apiversion>2.3.6</apiversion>
<apiversion>3.2.2</apiversion>
</permission>
<permission>
<name>android.permission.WAKE_LOCK</name>
<apiversion>3.2.2</apiversion>
<apiversion>4.0.1</apiversion>
</permission>
</permissions>
<file>./smali/com/google/android/gms/internal/do.java</file>
<line></line>
<protected>android/webkit/WebView;-$gt;onPause</protected>
<deleted>false</deleted>
</call>
<call>
<permissions>
<permission>
<name>android.permission.ACCESS_NETWORK_STATE</name>
<apiversion>2.2.3</apiversion>
<apiversion>2.3.6</apiversion>
<apiversion>3.2.2</apiversion>
</permission>
</permissions>
<file>./smali/com/google/android/gms/internal/do.java</file>
<line></line>
<protected>android/webkit/WebView;-$gt;onResume</protected>
<deleted>false</deleted>
</call>
<call>
<permissions>
<permission>
<name>android.permission.INTERNET</name>
<apiversion>4.1.1</apiversion>
<apiversion>2.2.3</apiversion>
<apiversion>2.3.6</apiversion>
<apiversion>3.2.2</apiversion>
<apiversion>4.0.1</apiversion>
</permission>
</permissions>
<file>./smali/com/google/android/gms/internal/ea.java</file>
<line></line>
<protected>java/net/URL;-$gt;openConnection</protected>
<deleted>false</deleted>
</call>
<call>
<permissions>
<permission>
<name>android.permission.INTERNET</name>
<apiversion>4.1.1</apiversion>
<apiversion>2.2.3</apiversion>
<apiversion>2.3.6</apiversion>
<apiversion>3.2.2</apiversion>
<apiversion>4.0.1</apiversion>
</permission>
</permissions>
<file>./smali/com/google/android/gms/internal/ea.java</file>
<line></line>
<protected>java/net/HttpURLConnection;-$gt;connect</protected>
<deleted>false</deleted>
</call>
<call>
<permissions>
<permission>
<name>android.permission.WAKE_LOCK</name>
<apiversion>4.1.1</apiversion>
<apiversion>2.2.3</apiversion>
<apiversion>2.3.6</apiversion>
<apiversion>3.2.2</apiversion>
<apiversion>4.0.1</apiversion>
</permission>
</permissions>
<file>./smali/com/google/android/gms/internal/bi.java</file>
<line></line>
<protected>android/widget/VideoView;-$gt;stopPlayback</protected>
<deleted>false</deleted>
</call>
<call>
<permissions>
<permission>
<name>android.permission.WAKE_LOCK</name>
<apiversion>4.1.1</apiversion>
<apiversion>2.2.3</apiversion>
<apiversion>2.3.6</apiversion>
<apiversion>3.2.2</apiversion>
<apiversion>4.0.1</apiversion>
</permission>
</permissions>
<file>./smali/com/google/android/gms/internal/bi.java</file>
<line></line>
<protected>android/widget/VideoView;-$gt;setVideoPath</protected>
<deleted>false</deleted>
</call>
<call>
<permissions>
<permission>
<name>android.permission.WAKE_LOCK</name>
<apiversion>4.1.1</apiversion>
<apiversion>2.2.3</apiversion>
<apiversion>2.3.6</apiversion>
<apiversion>3.2.2</apiversion>
<apiversion>4.0.1</apiversion>
</permission>
</permissions>
<file>./smali/com/google/android/gms/internal/bi.java</file>
<line></line>
<protected>android/widget/VideoView;-$gt;pause</protected>
<deleted>false</deleted>
</call>
<call>
<permissions>
<permission>
<name>android.permission.WAKE_LOCK</name>
<apiversion>4.1.1</apiversion>
<apiversion>2.2.3</apiversion>
<apiversion>2.3.6</apiversion>
<apiversion>3.2.2</apiversion>
<apiversion>4.0.1</apiversion>
</permission>
</permissions>
<file>./smali/com/google/android/gms/internal/bi.java</file>
<line></line>
<protected>android/widget/VideoView;-$gt;start</protected>
<deleted>false</deleted>
</call>
<call>
<permissions>
<permission>
<name>android.permission.VIBRATE</name>
<apiversion>4.1.1</apiversion>
<apiversion>2.2.3</apiversion>
<apiversion>2.3.6</apiversion>
<apiversion>3.2.2</apiversion>
<apiversion>4.0.1</apiversion>
</permission>
<permission>
<name>android.permission.WAKE_LOCK</name>
<apiversion>4.1.1</apiversion>
<apiversion>2.2.3</apiversion>
<apiversion>2.3.6</apiversion>
<apiversion>3.2.2</apiversion>
<apiversion>4.0.1</apiversion>
</permission>
</permissions>
<file>./smali/com/thunder4apps/arsenal/torchlight/WidgetReceiver.java</file>
<line>35</line>
<protected>android/os/Vibrator;-$gt;vibrate</protected>
<deleted>false</deleted>
</call>
<call>
<permissions>
<permission>
<name>android.permission.CAMERA</name>
<apiversion>4.1.1</apiversion>
<apiversion>2.2.3</apiversion>
<apiversion>2.3.6</apiversion>
<apiversion>3.2.2</apiversion>
<apiversion>4.0.1</apiversion>
</permission>
</permissions>
<file>./smali/com/thunder4apps/arsenal/torchlight/WidgetReceiver.java</file>
<line>61</line>
<protected>android/hardware/Camera;-$gt;open</protected>
<deleted>false</deleted>
</call>
<call>
<permissions>
<permission>
<name>android.permission.CAMERA</name>
<apiversion>4.1.1</apiversion>
<apiversion>2.2.3</apiversion>
<apiversion>2.3.6</apiversion>
<apiversion>3.2.2</apiversion>
<apiversion>4.0.1</apiversion>
</permission>
</permissions>
<file>./smali/com/thunder4apps/arsenal/torchlight/MainActivity$1.java</file>
<line>113</line>
<protected>android/hardware/Camera;-$gt;open</protected>
<deleted>false</deleted>
</call>
<call>
<permissions>
<permission>
<name>android.permission.VIBRATE</name>
<apiversion>4.1.1</apiversion>
<apiversion>2.2.3</apiversion>
<apiversion>2.3.6</apiversion>
<apiversion>3.2.2</apiversion>
<apiversion>4.0.1</apiversion>
</permission>
<permission>
<name>android.permission.WAKE_LOCK</name>
<apiversion>4.1.1</apiversion>
<apiversion>2.2.3</apiversion>
<apiversion>2.3.6</apiversion>
<apiversion>3.2.2</apiversion>
<apiversion>4.0.1</apiversion>
</permission>
</permissions>
<file>./smali/com/thunder4apps/arsenal/torchlight/MainActivity.java</file>
<line>84</line>
<protected>android/os/Vibrator;-$gt;vibrate</protected>
<deleted>false</deleted>
</call>
<call>
<permissions>
<permission>
<name>android.permission.CAMERA</name>
<apiversion>4.1.1</apiversion>
<apiversion>2.2.3</apiversion>
<apiversion>2.3.6</apiversion>
<apiversion>3.2.2</apiversion>
<apiversion>4.0.1</apiversion>
</permission>
</permissions>
<file>./smali/com/thunder4apps/arsenal/torchlight/MainActivity.java</file>
<line>175</line>
<protected>android/hardware/Camera;-$gt;open</protected>
<deleted>false</deleted>
</call>
</apicalls>
