<?xml version="1.0"?>
<calls>
  <call>
    <file>./smali/org/jariporola/batteryhero/Helper.java</file>
    <line>192</line>
    <permissions>
      <permission>
        <name>android.permission.VIBRATE</name>
      </permission>
    </permissions>
  </call>
  <call>
    <file>./smali/org/jariporola/batteryhero/connection/WiFiConnectionManager.java</file>
    <line>26</line>
    <permissions>
      <permission>
        <name>android.permission.CHANGE_WIFI_STATE</name>
      </permission>
    </permissions>
  </call>
  <call>
    <file>./smali/org/jariporola/batteryhero/connection/BluetoothConnectionManager.java</file>
    <line>25</line>
    <permissions>
      <permission>
        <name>android.permission.BLUETOOTH_ADMIN</name>
      </permission>
    </permissions>
  </call>
  <call>
    <file>./smali/org/jariporola/batteryhero/connection/BluetoothConnectionManager.java</file>
    <line>27</line>
    <permissions>
      <permission>
        <name>android.permission.BLUETOOTH_ADMIN</name>
      </permission>
    </permissions>
  </call>
</calls>
